mriqa/__init__.py
mriqa/dcmio.py
mriqa/fbirn.py
mriqa/ghosting.py
mriqa/mfxarray.py
mriqa/nistadc.py
mriqa/phantoms.py
mriqa/tools.py
mriqa/version.py
mriqa/reports/__init__.py
mriqa/reports/diffusion.py
mriqa/reports/flow.py
mriqa/reports/geometry.py
mriqa/reports/ghosting.py
mriqa/reports/noras.py
mriqa/reports/reports.py
mriqa/reports/resolution.py
mriqa/reports/slice.py
mriqa/reports/snr.py
mriqa/reports/spectroscopy.py
mriqa/reports/stability.py
mriqa/reports/uniformity.py
mriqa/xmlqa/__init__.py
mriqa/xmlqa/coilqa.py
mriqa-0.2.18.dist-info/METADATA
mriqa-0.2.18.dist-info/WHEEL
mriqa-0.2.18.dist-info/top_level.txt
mriqa-0.2.18.dist-info/RECORD
