Metadata-Version: 2.4
Name: mriqa
Version: 0.2.18
Summary: Tools for MRI QA
Home-page: https://bitbucket.org/rtrhd/mriqa.git
Download-URL: https://bitbucket.org/rtrhd/mriqa/get/v0.2.18.zip
Author: Ronald Hartley-Davies
Author-email: R.Hartley-Davies@physics.org
License: MIT
Keywords: mri qa phantom
Classifier: Development Status :: 4 - Beta
Classifier: Intended Audience :: Science/Research
Classifier: Topic :: Scientific/Engineering :: Medical Science Apps.
Classifier: License :: OSI Approved :: MIT License
Classifier: Operating System :: POSIX
Classifier: Programming Language :: Python :: 3.10
Classifier: Programming Language :: Python :: 3.11
Classifier: Programming Language :: Python :: 3.12
Classifier: Programming Language :: Python :: 3.13
Requires-Dist: numpy>=1.21.5
Requires-Dist: scipy>=1.8.0
Requires-Dist: matplotlib>=3.5.1
Requires-Dist: pandas>=1.3.5
Requires-Dist: xarray>=0.21.1
Requires-Dist: scikit-image>0.18.3
Requires-Dist: statsmodels>=0.13.2
Requires-Dist: pydicom>=2.2.2
Requires-Dist: dcmfetch>=0.3.2
Requires-Dist: dcmextras>=0.3.5
Dynamic: author
Dynamic: author-email
Dynamic: classifier
Dynamic: description
Dynamic: description-content-type
Dynamic: download-url
Dynamic: home-page
Dynamic: keywords
Dynamic: license
Dynamic: requires-dist
Dynamic: summary
